SuperAppVobla/__init__.py
SuperAppVobla/main.py
superappvobla-0.1.0.dist-info/METADATA
superappvobla-0.1.0.dist-info/WHEEL
superappvobla-0.1.0.dist-info/RECORD
