Metadata-Version: 2.1
Name: SuperAppVobla
Version: 0.1.0
Summary: 
Author: VoblaFish
Author-email: kuznec112233@mail.ru
Requires-Python: >=3.12,<4.0
Classifier: Programming Language :: Python :: 3
Classifier: Programming Language :: Python :: 3.12
Requires-Dist: pytest (>=8.2.2,<9.0.0)
